README.md
setup.py
terry_classify/__init__.py
terry_classify/pre_classifier.py
terry_classify.egg-info/PKG-INFO
terry_classify.egg-info/SOURCES.txt
terry_classify.egg-info/dependency_links.txt
terry_classify.egg-info/requires.txt
terry_classify.egg-info/top_level.txt