Metadata-Version: 2.1
Name: terry-classify
Version: 0.0.1.5
Summary: albert的分类
Home-page: https://github.com/napoler/albert_pytorch
Author: Terry Chan
Author-email: napoler2008@gmail.com
License: UNKNOWN
Platform: UNKNOWN
